torchcsprng/__init__.py
torchcsprng/_C.cpython-38-darwin.so
torchcsprng/version.py
torchcsprng/.dylibs/libc++.1.0.dylib
torchcsprng-0.2.1.dist-info/LICENSE
torchcsprng-0.2.1.dist-info/METADATA
torchcsprng-0.2.1.dist-info/RECORD
torchcsprng-0.2.1.dist-info/top_level.txt
torchcsprng-0.2.1.dist-info/WHEEL
